bfgsupport/__init__.py
bfgsupport/_version.py
bfgsupport/source/__init__.py
bfgsupport/source/acol_advancers_bid.py
bfgsupport/source/acol_advancers_later_bid.py
bfgsupport/source/acol_advancers_rebid.py
bfgsupport/source/acol_bidding.py
bfgsupport/source/acol_openers_bid.py
bfgsupport/source/acol_openers_later_bid.py
bfgsupport/source/acol_openers_rebid.py
bfgsupport/source/acol_openers_third_bid.py
bfgsupport/source/acol_overcallers_bid.py
bfgsupport/source/acol_overcallers_rebid.py
bfgsupport/source/acol_overcallers_third_bid.py
bfgsupport/source/acol_responders_bid.py
bfgsupport/source/acol_responders_later_bid.py
bfgsupport/source/acol_responders_rebid.py
bfgsupport/source/bfg_common.py
bfgsupport/source/blackwood.py
bfgsupport/source/board.py
bfgsupport/source/bridge_tools.py
bfgsupport/source/comment_xref.py
bfgsupport/source/create_deals.py
bfgsupport/source/dealer.py
bfgsupport/source/dealer_duo.py
bfgsupport/source/dealer_engine.py
bfgsupport/source/dealer_solo.py
bfgsupport/source/deploy.py
bfgsupport/source/file_objects.py
bfgsupport/source/hand.py
bfgsupport/source/images.py
bfgsupport/source/pbn.py
bfgsupport/source/pbn_loader.py
bfgsupport/source/pilimage.py
bfgsupport/source/player.py
bfgsupport/source/stages.py
bfgsupport/source/strategy_xref.py
bfgsupport/source/bidding/__init__.py
bfgsupport/source/bidding/acol_advancers_bid.py
bfgsupport/source/bidding/acol_advancers_later_bid.py
bfgsupport/source/bidding/acol_advancers_rebid.py
bfgsupport/source/bidding/acol_openers_bid.py
bfgsupport/source/bidding/acol_openers_later_bid.py
bfgsupport/source/bidding/acol_openers_rebid.py
bfgsupport/source/bidding/acol_openers_third_bid.py
bfgsupport/source/bidding/acol_overcallers_bid.py
bfgsupport/source/bidding/acol_overcallers_rebid.py
bfgsupport/source/bidding/acol_overcallers_third_bid.py
bfgsupport/source/bidding/acol_responders_bid.py
bfgsupport/source/bidding/acol_responders_later_bid.py
bfgsupport/source/bidding/acol_responders_rebid.py
bfgsupport-2.0.8.dist-info/LICENSE.txt
bfgsupport-2.0.8.dist-info/METADATA
bfgsupport-2.0.8.dist-info/WHEEL
bfgsupport-2.0.8.dist-info/top_level.txt
bfgsupport-2.0.8.dist-info/RECORD
