Metadata-Version: 2.1
Name: bfgsupport
Version: 2.0.8
Summary: """A collection of modules that supports dealing and bidding in Bid for Game applications."""
Home-page: https://psionman@bitbucket.org/psionman/bfgsupport.git
Download-URL: https://pypi.org/project/bfgsupport/
Author: jeff watkins
Author-email: support@bidforgame.com
License: MIT
Keywords: Application, User
License-File: LICENSE.txt
Requires-Dist: username
Requires-Dist: nose
Requires-Dist: pytest
